{
  "$schema": "https://mintlify.com/docs.json",
  "theme": "mint",
  "name": "Mint Starter Kit",
  "colors": {
    "primary": "#16A34A",
    "light": "#07C983",
    "dark": "#15803D"
  },
  "favicon": "/favicon.svg",
  "navigation": {
    "tabs": [
      {
        "tab": "Guides",
        "groups": [
          {
            "group": "Culture at Zemuria",
            "pages": [
              "index",
              "quickstart",
              "development",
              "Conclusion"
            ]
          },
          {
            "group": "POSH-ICC",
            "pages": [
              "POSH-ICC/Purpose",
              "POSH-ICC/Scope",
              "POSH-ICC/Applicability",
              "POSH-ICC/Definition",
              "POSH-ICC/Policy-Guidelines",
              "POSH-ICC/Grievance-redressal-mechanism",
              "POSH-ICC/Internal-Complaints-Committee",
              "POSH-ICC/Complaint-mechanism",
              "POSH-ICC/Inquiry-Process",
              "POSH-ICC/Confidentiality-and-Data-Protection",
              "POSH-ICC/Consequences-of-violation",
              "POSH-ICC/Monitoring-and-Review"
            ]
          
        
      },
          {
            "group": "Employee Handbook",
            "pages": [
              "employee-handbook/welcome",
              "employee-handbook/getting-to-know-our-company",
              "employee-handbook/Employment-Policies",
              "employee-handbook/equal-opportunity-employment",
              "employee-handbook/recruitment-and-selection-process",
              "employee-handbook/background-checks",
              "employee-handbook/referrals",
              "employee-handbook/attendance"
            ]          
          },
          {
            "group":"Workplace Polices",
            "pages":[
              "workplace-policies/Confidentiality-and-data-protection",
              "workplace-policies/workplace-harassment",
              "workplace-policies/workplace-violence",
              "workplace-policies/supporting-victims"
            ]
          }
        ]
      },
      {
        "tab": "API Reference",
        "groups": [
          {
            "group": "API Documentation",
            "pages": [
              "api-reference/introduction"
            ]
          },
          {
            "group": "Endpoint Examples",
            "pages": [
              "api-reference/endpoint/get",
              "api-reference/endpoint/create",
              "api-reference/endpoint/delete",
              "api-reference/endpoint/webhook"
            ]
          }
        ]
      }
    ],
    "global": {
      "anchors": [
        {
          "anchor": "Documentation",
          "href": "https://mintlify.com/docs",
          "icon": "book-open-cover"
        },
        {
          "anchor": "Community",
          "href": "https://mintlify.com/community",
          "icon": "slack"
        },
        {
          "anchor": "Blog",
          "href": "https://mintlify.com/blog",
          "icon": "newspaper"
        }
      ]
    }
  },
  "logo": {
    "light": "/logo/light.svg",
    "dark": "/logo/dark.svg"
  },
  "navbar": {
    "links": [
      {
        "label": "Support",
        "href": "mailto:hi@mintlify.com"
      }
    ],
    "primary": {
      "type": "button",
      "label": "Dashboard",
      "href": "https://dashboard.mintlify.com"
    }
  },
  "footer": {
    "socials": {
      "x": "https://x.com/mintlify",
      "github": "https://github.com/mintlify",
      "linkedin": "https://linkedin.com/company/mintlify"
    }
  }
}